{"episode_id":1849,"title":"如來光明 遍照十方","chapter_name":"","summary":"如來光明：象徵佛陀圓滿智慧，遍照十方，引導眾生開啟本具的如來藏性。\n開心門聞法：唯有用心聽聞、信受奉行，並落實於日常生活，才能引發內在智慧。\n萬物皆法：一切事物皆蘊含真理，應以感恩與懺悔心珍惜天地萬物及眾生恩。\n信解清淨：佛法需長久熏習，如法水點滴滋潤，由知識轉為智慧，才能遠離疑惑與後悔。\n《法華經》地位：如須彌山為群山之首、明月勝於群星、太陽破除黑暗，為諸經中最究竟的一乘實法。\n修學目標：藉由《法華經》開顯佛知佛見，破除無明煩惱，證入一乘實相，成就清淨智慧與圓滿覺悟。","full_text":"00:00 如來光明 遍照十方\n\n00:54⊙「如來光明，廣大奇妙，遍照十方，諸天光曜。一切眾生，見此光明，信解清淨，離諸疑悔。」\n\n各位，用心。用心才有辦法入如來藏性，人人本具；人人都有這樣的光明智慧，所以我們要展開我們的心，好好聽聞。外面這個光明，能夠將我們內心打開，光才能照進來，引出我們內心深藏如來光明的智性。還是要請大家要用心開心門，好好聽、了解，好好用在日常生活中，每天離不開這幾句話：「用心聽」、「聽入心」、「用在日常生活中」。這是期待，我們大家共同勉勵。\n\n「如來光明，廣大奇妙」，那是智慧。佛陀，他對每事、物，接觸到事、物，就以理同會。我們凡夫，看事就是事，看物就是物，我們若用心看，事非事、物非物，若又再深一層用心去體會，事還是分明的事，物還是有它真實物理的真諦。這就是我們要用心。如來看見所有的事物，無不都是諦理、事物分明，這就是「廣大奇妙」。他智慧「遍照十方」，他看這個東西，他就能夠了解其他的東西。\n\n樹種，眼睛所看無不都在這個環境，無不都是一顆種子來的，難道不是嗎？現在我們在看、我在看，還是同樣一顆種子。這顆種子那就是在山林裡，山林那一粒種子，那就是樹種成為木材。木材經過了日、月、星光，幾年的時間，幾十年的時間，說不定幾百年的時間，那個木材，人類已經侵入，就將那些木材這樣遷移來在人群生活中，成為我們生活中的椅子、桌子，所裝潢的東西，還是沒有離開用木材。\n\n所以我們這樣的空間、環境所用，該不該懺悔？它的所成就，是來自於日、月，時光。是啊，經過多少的時日，經過多長的時間，將那個山林樹木用在我們現在的家具當中。所以只要有用過家具，家中有做過裝潢，人人都有享用到。所以這是破壞山林之後，結果享受，給人的享受，所以人在享受還是要感恩、懺悔，凡事、凡物無不都是來自於眾生、天地間事事物物匯集來。\n\n所以我們常常說：「感恩，感恩眾生恩、父母恩、三寶恩。」這三恩我們應該要清楚。如來，佛寶啊，佛陀來人間，在人間見苦、人間修行、人間覺悟，於人間體會，體會人間所有的道理，天地、宇宙，所以他的智慧照徹了所有的一切，所以「如來光明」，光明就是智慧，那個智慧所接觸、看到，見一物就是知宇宙萬物的生態、道理，這就是如來的光明，就是如來的智慧，他「廣大奇妙」。\n\n我們大家要很有信心，接受佛陀他所說的教法。人間說《法華經》，就是要讓我們大家很清楚了解，經的當中，不論山河大地、天文地理，無事不點到，就是這樣一一為我們點到。所以如來這種「遍照十方，諸天光曜」。在這個人間裡什麼最光明？莫過於太陽之光。\n\n剛才我要走出來，看到晨曦還在雲端之中，雲還未全開，陽光浮出海面，慢慢浮出來，就是已經晨曦有一點露出來了。我轉過頭，往裡面走進來，相信在這幾分鐘的時間，那道光應該出來了。這就是我們在時間過程我們不會去感覺到，沒有感覺宇宙的真實，那種法輪的輪轉。\n\n日、月無不都是在天體之中，與地球這樣在互動；地球轉了，轉過了日影，轉過了月光，日夜不斷在輪轉，守著它的軌道這樣在轉。所以我們在地球上，我們更加要了解佛陀所說的真理。在這個地球宇宙間、大自然界，這光，光是如何過來的？是地球轉過去？或是太陽升出來？這我們就要用心。是地球轉？或者是太陽升？\n\n現在這個時代已經是天文、地理學都已經很發達，專心研究，專心學者去研究、去推測。所以我們那個推測與那個氣候，什麼時候有風、有雨，什麼時候會大風、大雨，什麼時候是豔陽、很熱，那個溫度多高，一一都讓我們很清楚。\n\n每天都能夠知道，「明天會下雨」、「明天太陽會很大」，在我們的生活要準備明天，我們先知道明天，我們懂得準備。明天是下雨天，我們要準備出門預防的工具；大太陽，我們要準備什麼，有什麼樣的活動，我們要用什麼樣的工具來預防陽光大，或者是會下雨。現在都讓我們提前預測、準備。\n\n所以說來，我們現在的人間是很有福，好像在享天福一樣，我們要大家很知福。要利用在福報這個時間，我們對於佛法就要多深入。有時間、有因緣，因緣成熟，讓我們時會在一起，我們要感恩啊！所以「如來光明，廣大奇妙，遍照十方，諸天光曜」。這樣的境界，我們要好好用感恩心，多把握、多利用。這不是只有看文字，我們要用心接受、利用、珍惜，珍惜一切。\n\n「一切眾生」，要好好了解，「見此光明，信解清淨，離諸疑悔」，我們修行就是要這些，懂得把握因緣。佛法難遇，我們能得到佛法來指引我們的方向，我們好好方向把握，所以我們看的是一片的光明，光明已經開啟了。我們若開心門，開啟了，就能夠看到光明。\n\n就像我剛才走，走到外面，腳稍停一下，向遠方看，那道曦光，它開始將要浮現了。若沒有走出來，我的心門無法在這個地方對照，所以就是走出來了，心門對照著陽光，對照著，坐在這裡對大家，與我面前這些經文字句，是因為我的心門打開了。昨天的用心將這些字句整理好了，我靠著前面(螢幕)來會遇我昨天的用心；昨天的用心，要感恩過去累積的心得。\n\n所以我們向前看，向後思考、回憶，這就是我們平時要用的心。在現在看前面(螢幕)文字顯現出來。「見此光明，信解清淨」，我們了解，法清楚了，我們的內心要啟發出我們的「信」，相信。佛陀在那個時代，並沒有想要說什麼法，經過草稿，沒有。但是口口相傳，後來的人將心得這樣片句「如是我聞」，一句一句這樣寫起來，才開始將佛陀的說法連句抄寫。這都經過人，人的知識來累積了佛陀的智慧。\n\n佛陀的智慧是從他的心，再體會宇宙的真理說出來的，不是草稿來說的，是智慧這樣自然說出來。後代的人體會了解、體會了解，累積才慢慢成為文字。現在我們聽聲，聽人的經驗累積，同樣成為文字，文字來說給大家聽。現在眼前(螢幕)的文字，與《法華經》的經文是不同，但是它是《法華經》當中所意含的體會。經典文字外的體會，大家要從體會中，來認識《法華經》，將《法華經》的道理用在生活中。\n\n這沒有離開我們自己，本身的知識轉成智慧，大家要很用心。「信解清淨」，我們若用我們的，僅僅用我們的知識無法清淨，一定要用智慧，這幾天就一直對大家提醒「轉識成智」。所以不斷反覆對大家這樣說，就是要說的是「信解清淨」，這個清淨就是知識的智慧。因為知識，「我知道了、我看到了，我了解、我認識它。」光了解、認識，這是表面的，不是浸潤。\n\n昨天說，那個滋潤，法水滋潤是這樣點滴、點滴，不斷潤溼，不是這樣很乾燥的，一桶水潑下去，不是。這桶水是這樣慢慢地滴、慢慢地點，這樣滴下去。同樣，就像人的身體，四大不調了，不是藥吃下去就好，他還要再打點滴、點滴，一小時滴幾十滴，這樣慢慢滴，這就是浸潤，需要的就是要讓你一點一滴慢慢去接受。\n\n這就像我們求法，用心，心要清淨，清淨心從信，信心來，我們要有信心。而這個信心求法，才能夠去體會、了解，不是「我知道、知道」，我知道之後，這樣、這樣為你安排，你就是照我的安排定點去做。」這樣彼此都無所得，那種速，很快。皮膚過水而已，並沒有保溼在。所以這樣為你安排，我安排人的人，我也無所得，一時的知識；被安排的，就是你如何安排，我就是站在哪裡。這樣動作過了之後，與我們又沒有關係。\n\n所以我們要好好用心，自己打從內心的發心。發心，我們起信，起這個念的信心，這念信心，信、願、行。所以有信心才會想要去了解；多了解，得一句，我會拳拳服膺在我的內心，這才是真正的信解。心沒有其他複雜的事情，就是一心。我，《法華經》，我就是專心在《法華經》。《法華經》一字一字，一字一句，一四句偈；五字一句，這四句編一偈，像這樣一一了解。\n\n不就是四句，四句一偈？這一字一字編起來，就是四句一偈。雖然是我這樣寫，但是編起來，我就認為這樣是一偈；一字一字寫，寫四句一偈。同樣的道理，經文也是這樣，從所心得將它濃縮。「法外別傳」，就是說這本經心得，又用在其它的心得返回來，這我們就能夠了解。\n\n「一切眾生，見此光明」，這個光明是佛陀的智慧，他說《法華經》就是從他的智慧中講出來的，是應眾生的根機，在人間所需要，開眾生的心門，要見解佛陀的教法。所以「見此光明」，我們就要信解，信解就是要離開很多的疑悔，你既然要信了，有信就不疑，就不可疑，所以有信無疑，才叫做「離諸疑悔」。\n\n讀這部經沒有後悔，我們這輩子所做的沒有後悔，同樣的道理。我們想好，一念間，想好，做；做過了，再也沒有後悔。這也是我最近在說，看到大家回來分享，就如看到三十年前(1989年)(慈濟護專)第一屆、第二屆的學生，現在是主管了回來開會了。是啊，人才就是在時間培養出來。\n\n三十幾年前學校啟用，現在(2020年)學校三十一年了，第一屆的學生現在成為主管，職業成為主管。所以時間這樣的過程，就會說：「啊，沒有後悔，沒有後悔那個時候的辛苦，人才已經成就了，沒有後悔。」所以「離諸疑悔」，沒有後悔的一生。就是我們要很用心去體會。\n\n經文，《法華經》當中，我們前文昨天所說的，已經是說「又如土山」。因為經文當中談天說地，說我們人間的地理，有種種諸山，山、河、溪水等等，又再說到山、海等等，這都在我們的世間裡，《法華經》當中就全都為我們點出來，這就是人間世界。這人間世界，現在經文這樣說，\n\n33:31⊙「又如土山、黑山、小鐵圍山、大鐵圍山、及十寶山眾山之中，須彌山為第一，此法華經亦復如是，於諸經中最為其上。」《法華經藥王菩薩本事品二十三》\n\n在這些大地上很多很多的山，在世界上喜馬拉雅山是最高，喜馬拉雅山就是叫做須彌山。經文之中叫做須彌山，這須彌山是群山之王。所以「此法華經亦復如是，於諸經中最為其上」。《法華經》在所有的經典是至高無上，這是《法華經》。佛陀已經明說，過去的經也是佛陀說的，現在來到《法華經》，他就向大家說《法華經》是諸經之上，至高無上，它涵蓋很廣。\n\n35:29⊙「又如眾星之中月天子最為第一，此法華經亦復如是，於千萬億種諸經法中最為照明。」《法華經藥王菩薩本事品二十三》\n\n這是經文。眾星之中月天子為第一，那就是「星宿中之王」，那就是群星之中「最為明亮」，那就是月天子。\n\n36:18⊙又如眾星之中月天子最為第一：星宿中之王，群星中最為明亮。\n\n看看晚上，若是在下半月開始，月亮開始一直出來了，到了農曆十五日，月是正圓。看看天空，星，我們星，星光，小顆的星光很多，滿天，但是月光若出來，還是月光為第一。所以它是群星中最為明亮，所有的星在夜空，所有天空中，月是最為明亮。\n\n⊙此法華經亦復如是：又如月天子。\n\n37:45⊙星月夜現，朗夜之光，星不及月，喻前施設權教乃照世之典，但權不及實者。\n\n「星月夜現」，就「朗夜之光」，它能夠照徹晚上的光。「星不及月」，譬如前面佛陀所施教的是權教，是方便教。它雖然是方便教，好像那個星星一樣，也是亮麗在天空中。但是這是方便的教法，叫做權教，權教不及實教。\n\n《法華經》是一實教，《法華經》是一實相的教理。過去所談的，就是眾生根機，適合眾生的根機，用小教投小根機；中，大法，那就是隨眾生機投教。來到「法華」，它是一個圓滿的大教法。\n\n39:35⊙於千萬億種諸經法中最為照明：於餘諸多方便教，光照三乘，此法華經慧光所照究竟覺。\n\n「於千萬億種諸經法中最為照明」。所以於餘諸多方便教法，是「光照三乘」。這些方便教法就是好像星光照。「此法華經慧光」，所照是最究竟覺，最究竟的覺悟，就是圓的光。\n\n40:37⊙照明二字取喻，以大寶在暗，非燈莫照。一乘實相，隱於藏識，不得今經開示，眾生佛知佛見不明，故最為照明也。\n\n42:31⊙「又如日天子能除諸闇，此經亦復如是，能破一切不善之闇。」《法華經藥王菩薩本事品二十三》\n\n42:51⊙日當中天，幽衢頓破；此經入耳，昏障潛消。以此經明一乘實相，能破一切眾生不善惑闇故。\n\n44:34⊙又如日天子能除諸闇：日光出時，破諸幽暗。\n\n45:20⊙此經亦復如是，能破一切不善之闇：究盡三惑，成一實道。\n\n～證嚴上人講述於2020年7月31日～\n","is_edited":true,"edited_by":"Mental Kuo","edited_date":"2026/06/30","youtube_url":"https://www.youtube.com/watch?v=JnL89rMy5pg","edit_history":[{"date":"2026/06/30","author":"Mental Kuo","mode":"summary"}],"chapter_id":23}